fastapi_async_sql/__init__.py
fastapi_async_sql/exceptions.py
fastapi_async_sql/filtering.py
fastapi_async_sql/middlewares.py
fastapi_async_sql/models.py
fastapi_async_sql/pagination.py
fastapi_async_sql/repositories.py
fastapi_async_sql/utils/__init__.py
fastapi_async_sql/utils/partial.py
fastapi_async_sql/utils/string.py
fastapi_async_sql-0.1.0.dist-info/METADATA
fastapi_async_sql-0.1.0.dist-info/WHEEL
fastapi_async_sql-0.1.0.dist-info/RECORD
