Metadata-Version: 2.3
Name: fastapi-async-sql
Version: 0.1.0
Summary: Common utilities for Async SQL FastAPI applications
Requires-Python: >=3.12
Requires-Dist: fastapi-filter[sqlalchemy]<3.0.0,>=2.0.0
Requires-Dist: fastapi-pagination<0.13.0,>=0.12.26
Requires-Dist: fastapi<0.113.0,>=0.100.0
Requires-Dist: inflect<8.0.0,>=7.3.1
Requires-Dist: sqlmodel<0.1.0,>=0.0.21
Provides-Extra: docs
Requires-Dist: mkdocs-git-revision-date-localized-plugin>=1.2.7; extra == 'docs'
Requires-Dist: mkdocs-material>=9.5.33; extra == 'docs'
Provides-Extra: lint
Requires-Dist: pre-commit>=3.8.0; extra == 'lint'
Requires-Dist: ruff-lsp>=0.0.55; extra == 'lint'
Requires-Dist: ruff>=0.6.2; extra == 'lint'
Provides-Extra: test
Requires-Dist: aiosqlite>=0.20.0; extra == 'test'
Requires-Dist: factory-boy>=3.3.1; extra == 'test'
Requires-Dist: httpx>=0.27.2; extra == 'test'
Requires-Dist: pytest-asyncio>=0.24.0; extra == 'test'
Requires-Dist: pytest-cov>=5.0.0; extra == 'test'
Requires-Dist: pytest-mock>=3.14.0; extra == 'test'
Requires-Dist: pytest>=8.3.2; extra == 'test'
